{"name":"ProvideComment","identifier":"CCEU70138X","description":null,"slotTypeName":"AMAZON.Confirmation","obfuscationSetting":null,"valueElicitationSetting":{"slotCaptureSetting":{"codeHook":null,"captureResponse":null,"captureNextStep":{"sessionAttributes":{},"intent":{"name":null,"slots":{}},"dialogAction":{"type":"EvaluateConditional","slotToElicit":null,"suppressNextMessage":null}},"captureConditional":{"isActive":true,"conditionalBranches":[{"name":"Yes","response":null,"condition":{"expressionString":"{ProvideComment} = \"Yes\""},"nextStep":{"sessionAttributes":{},"intent":{"name":null,"slots":{}},"dialogAction":{"type":"ElicitSlot","slotToElicit":"Comment","suppressNextMessage":null}}}],"defaultBranch":{"response":null,"nextStep":{"sessionAttributes":{},"intent":{"name":null,"slots":{}},"dialogAction":{"type":"ConfirmIntent","slotToElicit":null,"suppressNextMessage":null}}}},"failureResponse":null,"failureNextStep":{"sessionAttributes":{},"intent":{"name":"FallbackIntent","slots":{}},"dialogAction":{"type":"StartIntent","slotToElicit":null,"suppressNextMessage":null}},"failureConditional":null,"elicitationCodeHook":{"enableCodeHookInvocation":true,"invocationLabel":null}},"slotConstraint":"Required","promptSpecification":{"messageGroupsList":[{"message":{"ssmlMessage":null,"customPayload":null,"plainTextMessage":{"value":"Do you have any request or comments you want to provide for the hotel?"},"imageResponseCard":null},"variations":[{"ssmlMessage":null,"customPayload":null,"plainTextMessage":{"value":"Do you have any requests or comments for the hotel? Please say yes or no."},"imageResponseCard":null},{"ssmlMessage":null,"customPayload":null,"plainTextMessage":{"value":"If you have a request, for example,an early check-in, say yes. Otherwise say no."},"imageResponseCard":null}]}],"maxRetries":4,"messageSelectionStrategy":"Ordered","allowInterrupt":true,"promptAttemptsSpecification":{"Retry2":{"textInputSpecification":{"startTimeoutMs":30000},"allowedInputTypes":{"allowAudioInput":true,"allowDTMFInput":true},"audioAndDTMFInputSpecification":{"audioSpecification":{"endTimeoutMs":640,"maxLengthMs":15000},"startTimeoutMs":4000,"dtmfSpecification":{"maxLength":513,"endTimeoutMs":5000,"deletionCharacter":"*","endCharacter":"#"}},"allowInterrupt":true},"Retry4":{"textInputSpecification":{"startTimeoutMs":30000},"allowedInputTypes":{"allowAudioInput":true,"allowDTMFInput":true},"audioAndDTMFInputSpecification":{"audioSpecification":{"endTimeoutMs":640,"maxLengthMs":15000},"startTimeoutMs":4000,"dtmfSpecification":{"maxLength":513,"endTimeoutMs":5000,"deletionCharacter":"*","endCharacter":"#"}},"allowInterrupt":true},"Retry3":{"textInputSpecification":{"startTimeoutMs":30000},"allowedInputTypes":{"allowAudioInput":true,"allowDTMFInput":true},"audioAndDTMFInputSpecification":{"audioSpecification":{"endTimeoutMs":640,"maxLengthMs":15000},"startTimeoutMs":4000,"dtmfSpecification":{"maxLength":513,"endTimeoutMs":5000,"deletionCharacter":"*","endCharacter":"#"}},"allowInterrupt":true},"Initial":{"textInputSpecification":{"startTimeoutMs":30000},"allowedInputTypes":{"allowAudioInput":true,"allowDTMFInput":true},"audioAndDTMFInputSpecification":{"audioSpecification":{"endTimeoutMs":640,"maxLengthMs":15000},"startTimeoutMs":4000,"dtmfSpecification":{"maxLength":513,"endTimeoutMs":5000,"deletionCharacter":"*","endCharacter":"#"}},"allowInterrupt":true},"Retry1":{"textInputSpecification":{"startTimeoutMs":30000},"allowedInputTypes":{"allowAudioInput":true,"allowDTMFInput":true},"audioAndDTMFInputSpecification":{"audioSpecification":{"endTimeoutMs":640,"maxLengthMs":15000},"startTimeoutMs":4000,"dtmfSpecification":{"maxLength":513,"endTimeoutMs":5000,"deletionCharacter":"*","endCharacter":"#"}},"allowInterrupt":true}}},"defaultValueSpecification":null,"sampleUtterances":null,"waitAndContinueSpecification":null,"slotResolutionSetting":{"slotResolutionStrategy":"EnhancedFallback"}},"multipleValuesSetting":null}